{"progress": 62, "message": "Completed 18/199", "status": "processing", "logs": "[12:57:43] Initializing...\n[12:57:45] Generating Spanish script...\n[12:57:46] Processing sentences for audio...\n[12:57:46] \ud83c\udf99\ufe0f Generating Spanish TTS with Chatterbox (language_id='es')...\n[13:15:52] \ud83d\udd0d Transcribing audio with Assembly AI...\n[13:16:13] Creating Spanish subtitles...\n[13:16:14] \ud83c\udf32 Processing nature visuals...\n[13:16:19] Completed 1/199\n[13:16:20] Completed 2/199\n[13:16:21] Completed 3/199\n[13:16:22] Completed 4/199\n[13:16:23] Completed 5/199\n[13:16:24] Completed 6/199\n[13:16:25] Completed 7/199\n[13:16:26] Completed 8/199\n[13:16:27] Completed 9/199\n[13:16:28] Completed 10/199\n[13:16:29] Completed 11/199\n[13:16:30] Completed 12/199\n[13:16:31] Completed 13/199\n[13:16:32] Completed 14/199\n[13:16:33] Completed 15/199\n[13:16:34] Completed 16/199\n[13:16:35] Completed 17/199\n[13:16:36] Completed 18/199", "timestamp": 1772630196.6487648}