{"progress": 100, "message": "\u2705 Spanish Nature Video Complete!\n\ud83c\udf99\ufe0f Chatterbox Spanish TTS (language_id='es')\n\ud83d\udd0d Assembly AI Spanish subtitles\n\ud83c\udf32 Pure Nature Videos\n\u26a1 GPU Accelerated\n\ud83d\udcf9 No Subs: https://drive.google.com/file/d/1I_Tt-VxA16YMn9aAY3lPMcQnC1xvry4w/view\n\ud83d\udcf9 With Subs: https://drive.google.com/file/d/1T-Bg6w3JcvhOtEvaurOOSDbM1JihgpYK/view", "status": "completed", "logs": "[10:26:28] Completed 174/199\n[10:26:29] Completed 175/199\n[10:26:29] Completed 176/199\n[10:26:30] Completed 177/199\n[10:26:31] Completed 178/199\n[10:26:32] Completed 179/199\n[10:26:33] Completed 180/199\n[10:26:33] Completed 181/199\n[10:26:34] Completed 182/199\n[10:26:35] Completed 183/199\n[10:26:36] Completed 184/199\n[10:26:36] Completed 185/199\n[10:26:37] Completed 186/199\n[10:26:38] Completed 187/199\n[10:26:39] Completed 188/199\n[10:26:39] Completed 189/199\n[10:26:40] Completed 190/199\n[10:26:41] Completed 191/199\n[10:26:42] Completed 192/199\n[10:26:43] Completed 193/199\n[10:26:44] Completed 194/199\n[10:26:44] Completed 195/199\n[10:26:45] Completed 196/199\n[10:26:46] Completed 197/199\n[10:26:46] Completed 198/199\n[10:26:47] Completed 199/199\n[10:28:01] Rendering 900p version...\n[10:30:37] Rendering 1080p with subtitles...\n[10:34:49] \u2601\ufe0f Uploading to Google Drive...\n[10:35:16] \u2705 Spanish Nature Video Complete!\n\ud83c\udf99\ufe0f Chatterbox Spanish TTS (language_id='es')\n\ud83d\udd0d Assembly AI Spanish subtitles\n\ud83c\udf32 Pure Nature Videos\n\u26a1 GPU Accelerated\n\ud83d\udcf9 No Subs: https://drive.google.com/file/d/1I_Tt-VxA16YMn9aAY3lPMcQnC1xvry4w/view\n\ud83d\udcf9 With Subs: https://drive.google.com/file/d/1T-Bg6w3JcvhOtEvaurOOSDbM1JihgpYK/view", "timestamp": 1775385316.8340418, "file_io_url": "https://drive.google.com/file/d/1I_Tt-VxA16YMn9aAY3lPMcQnC1xvry4w/view"}