{"progress": 100, "message": "\u2705 Spanish Nature Video Complete!\n\ud83c\udf99\ufe0f Chatterbox Spanish TTS (language_id='es')\n\ud83d\udd0d Assembly AI Spanish subtitles\n\ud83c\udf32 Pure Nature Videos\n\u26a1 GPU Accelerated\n\ud83d\udcf9 No Subs: https://drive.google.com/file/d/1z4psfVkKIqBRLZloU0eA6gkA0vAI9zjN/view\n\ud83d\udcf9 With Subs: https://drive.google.com/file/d/1G3z7XTtHdrKbySCaBGDPTZ_wQG7DI4-R/view", "status": "completed", "logs": "[11:07:58] Completed 151/176\n[11:07:59] Completed 152/176\n[11:08:00] Completed 153/176\n[11:08:01] Completed 154/176\n[11:08:02] Completed 155/176\n[11:08:03] Completed 156/176\n[11:08:04] Completed 157/176\n[11:08:05] Completed 158/176\n[11:08:06] Completed 159/176\n[11:08:07] Completed 160/176\n[11:08:09] Completed 161/176\n[11:08:10] Completed 162/176\n[11:08:11] Completed 163/176\n[11:08:12] Completed 164/176\n[11:08:13] Completed 165/176\n[11:08:14] Completed 166/176\n[11:08:15] Completed 167/176\n[11:08:16] Completed 168/176\n[11:08:18] Completed 169/176\n[11:08:19] Completed 170/176\n[11:08:20] Completed 171/176\n[11:08:21] Completed 172/176\n[11:08:22] Completed 173/176\n[11:08:24] Completed 174/176\n[11:08:25] Completed 175/176\n[11:08:26] Completed 176/176\n[11:09:45] Rendering 900p version...\n[11:12:06] Rendering 1080p with subtitles...\n[11:15:48] \u2601\ufe0f Uploading to Google Drive...\n[11:16:37] \u2705 Spanish Nature Video Complete!\n\ud83c\udf99\ufe0f Chatterbox Spanish TTS (language_id='es')\n\ud83d\udd0d Assembly AI Spanish subtitles\n\ud83c\udf32 Pure Nature Videos\n\u26a1 GPU Accelerated\n\ud83d\udcf9 No Subs: https://drive.google.com/file/d/1z4psfVkKIqBRLZloU0eA6gkA0vAI9zjN/view\n\ud83d\udcf9 With Subs: https://drive.google.com/file/d/1G3z7XTtHdrKbySCaBGDPTZ_wQG7DI4-R/view", "timestamp": 1775474197.1475093, "file_io_url": "https://drive.google.com/file/d/1z4psfVkKIqBRLZloU0eA6gkA0vAI9zjN/view"}