{"progress": 64, "message": "Completed 18/91", "status": "processing", "logs": "[01:52:09] Initializing...\n[01:52:11] Generating Spanish script...\n[01:52:12] Processing sentences for audio...\n[01:52:13] \ud83c\udf99\ufe0f Generating Spanish TTS with Chatterbox (language_id='es')...\n[02:07:58] \ud83d\udd0d Transcribing audio with Assembly AI...\n[02:08:22] Creating Spanish subtitles...\n[02:08:23] \ud83c\udf32 Processing nature visuals...\n[02:08:29] Completed 1/91\n[02:08:30] Completed 2/91\n[02:08:31] Completed 3/91\n[02:08:32] Completed 4/91\n[02:08:33] Completed 5/91\n[02:08:34] Completed 6/91\n[02:08:35] Completed 7/91\n[02:08:37] Completed 8/91\n[02:08:38] Completed 9/91\n[02:08:39] Completed 10/91\n[02:08:40] Completed 11/91\n[02:08:41] Completed 12/91\n[02:08:42] Completed 13/91\n[02:08:43] Completed 14/91\n[02:08:45] Completed 15/91\n[02:08:46] Completed 16/91\n[02:08:47] Completed 17/91\n[02:08:48] Completed 18/91", "timestamp": 1775354928.385358}