{"progress": 76, "message": "Completed 62/93", "status": "processing", "logs": "[10:21:09] Completed 33/93\n[10:21:12] Completed 34/93\n[10:21:12] Completed 35/93\n[10:21:13] Completed 36/93\n[10:21:14] Completed 37/93\n[10:21:15] Completed 38/93\n[10:21:16] Completed 39/93\n[10:21:17] Completed 40/93\n[10:21:18] Completed 41/93\n[10:21:20] Completed 42/93\n[10:21:21] Completed 43/93\n[10:21:23] Completed 44/93\n[10:21:24] Completed 45/93\n[10:21:25] Completed 46/93\n[10:21:26] Completed 47/93\n[10:21:29] Completed 48/93\n[10:21:30] Completed 49/93\n[10:21:31] Completed 50/93\n[10:21:33] Completed 51/93\n[10:21:34] Completed 52/93\n[10:21:35] Completed 53/93\n[10:21:36] Completed 54/93\n[10:21:38] Completed 55/93\n[10:21:39] Completed 56/93\n[10:21:39] Completed 57/93\n[10:21:40] Completed 58/93\n[10:21:42] Completed 59/93\n[10:21:43] Completed 60/93\n[10:21:44] Completed 61/93\n[10:21:46] Completed 62/93", "timestamp": 1776594106.010401}