{"progress": 100, "message": "\u2705 Spanish Nature Video Complete!\n\ud83c\udf99\ufe0f Chatterbox Spanish TTS (language_id='es')\n\ud83d\udd0d Assembly AI Spanish subtitles\n\ud83c\udf32 Pure Nature Videos\n\u26a1 GPU Accelerated\n\ud83d\udcf9 No Subs: https://drive.google.com/file/d/15lv_MOlJIG7KfDjUQeBn4MnWnBcgA_5k/view\n\ud83d\udcf9 With Subs: https://drive.google.com/file/d/1upoLWfuW3XqYt2_d-XPhacxqL_ciF77T/view", "status": "completed", "logs": "[13:12:33] Completed 195/220\n[13:12:34] Completed 196/220\n[13:12:36] Completed 197/220\n[13:12:37] Completed 198/220\n[13:12:38] Completed 199/220\n[13:12:39] Completed 200/220\n[13:12:41] Completed 201/220\n[13:12:42] Completed 202/220\n[13:12:45] Completed 203/220\n[13:12:47] Completed 204/220\n[13:12:48] Completed 205/220\n[13:12:51] Completed 206/220\n[13:12:52] Completed 207/220\n[13:12:53] Completed 208/220\n[13:12:56] Completed 209/220\n[13:12:57] Completed 210/220\n[13:12:58] Completed 211/220\n[13:12:59] Completed 212/220\n[13:13:01] Completed 213/220\n[13:13:02] Completed 214/220\n[13:13:03] Completed 215/220\n[13:13:04] Completed 216/220\n[13:13:05] Completed 217/220\n[13:13:07] Completed 218/220\n[13:13:08] Completed 219/220\n[13:13:09] Completed 220/220\n[13:14:33] Rendering 900p version...\n[13:17:01] Rendering 1080p with subtitles...\n[13:20:57] \u2601\ufe0f Uploading to Google Drive...\n[13:22:00] \u2705 Spanish Nature Video Complete!\n\ud83c\udf99\ufe0f Chatterbox Spanish TTS (language_id='es')\n\ud83d\udd0d Assembly AI Spanish subtitles\n\ud83c\udf32 Pure Nature Videos\n\u26a1 GPU Accelerated\n\ud83d\udcf9 No Subs: https://drive.google.com/file/d/15lv_MOlJIG7KfDjUQeBn4MnWnBcgA_5k/view\n\ud83d\udcf9 With Subs: https://drive.google.com/file/d/1upoLWfuW3XqYt2_d-XPhacxqL_ciF77T/view", "timestamp": 1773321720.979088, "file_io_url": "https://drive.google.com/file/d/15lv_MOlJIG7KfDjUQeBn4MnWnBcgA_5k/view"}